limetr/__about__.py
limetr/__init__.py
limetr/core.py
limetr/data.py
limetr/utils.py
limetr/variable.py
limetr/visual.py
limetr/linalg/__init__.py
limetr/linalg/smooth_mapping.py
limetr/stats/__init__.py
limetr/stats/prior.py
limetr-0.1.1.dist-info/LICENSE
limetr-0.1.1.dist-info/METADATA
limetr-0.1.1.dist-info/WHEEL
limetr-0.1.1.dist-info/top_level.txt
limetr-0.1.1.dist-info/RECORD
