Metadata-Version: 2.1
Name: limetr
Version: 0.1.1
Summary: limetr: linear mixed effects model with trimming.
Home-page: https://github.com/zhengp0/limetr
Author: Peng Zheng
Author-email: zhengp@uw.eud
License: MIT License
Platform: UNKNOWN
Requires-Dist: numpy
Requires-Dist: scipy
Requires-Dist: spmat
Requires-Dist: matplotlib
Provides-Extra: dev
Requires-Dist: pytest ; extra == 'dev'
Requires-Dist: pytest-mock ; extra == 'dev'
Provides-Extra: docs
Provides-Extra: test
Requires-Dist: pytest ; extra == 'test'
Requires-Dist: pytest-mock ; extra == 'test'
